spred/__init__.py
spred/main.py
spred/commands/__init__.py
spred/commands/analyze.py
spred/commands/enrich.py
spred/commands/plot.py
spred/commands/run_all.py
spred/resource/ref/.DS_Store
spred/resource/ref/GRCh38_v42/.keep
spred/resource/ref/GRCm39_M36/.keep
spred/tests/test_main.py
spred/tools/__init__.py
spred/tools/downloader.py
spred/tools/iso_gene_differential.py
spred/tools/splicing_genes.py
spred-0.1.1.dist-info/LICENSE
spred-0.1.1.dist-info/METADATA
spred-0.1.1.dist-info/WHEEL
spred-0.1.1.dist-info/entry_points.txt
spred-0.1.1.dist-info/top_level.txt
spred-0.1.1.dist-info/RECORD
