Metadata-Version: 2.1
Name: spred
Version: 0.1.1
Summary: Splicing-regulatory Driver Genes Identification Tool
Author-email: Chenqing Zheng <zhengchenqing@aliyun.com>
License: MIT
Project-URL: Homepage, https://github.com/yourusername/asge-demo
Requires-Python: >=3.10
License-File: LICENSE
Requires-Dist: click
Requires-Dist: pandas
Requires-Dist: numpy
Requires-Dist: scipy
Requires-Dist: statsmodels
Requires-Dist: pydeseq2 ==0.5.1
Requires-Dist: gseapy ==1.1.6
Requires-Dist: seaborn ==0.13.2
Provides-Extra: test
Requires-Dist: pytest ; extra == 'test'
Requires-Dist: pytest-cov ; extra == 'test'
Requires-Dist: click ; extra == 'test'
